odoo/addons/beesdoo_website_theme/README.rst
odoo/addons/beesdoo_website_theme/__init__.py
odoo/addons/beesdoo_website_theme/__manifest__.py
odoo/addons/beesdoo_website_theme/readme/CONTRIBUTORS.rst
odoo/addons/beesdoo_website_theme/readme/DESCRIPTION.rst
odoo/addons/beesdoo_website_theme/static/description/index.html
odoo/addons/beesdoo_website_theme/static/src/font/BebasNeue-Bold.ttf
odoo/addons/beesdoo_website_theme/static/src/font/Roboto-Bold.ttf
odoo/addons/beesdoo_website_theme/static/src/font/Roboto-BoldItalic.ttf
odoo/addons/beesdoo_website_theme/static/src/font/Roboto-Italic.ttf
odoo/addons/beesdoo_website_theme/static/src/font/Roboto-Regular.ttf
odoo/addons/beesdoo_website_theme/static/src/less/beesdoo_website_design.less
odoo/addons/beesdoo_website_theme/views/assets.xml
odoo12_addon_beesdoo_website_theme-12.0.0.0.1.99.dev1.dist-info/METADATA
odoo12_addon_beesdoo_website_theme-12.0.0.0.1.99.dev1.dist-info/WHEEL
odoo12_addon_beesdoo_website_theme-12.0.0.0.1.99.dev1.dist-info/top_level.txt
odoo12_addon_beesdoo_website_theme-12.0.0.0.1.99.dev1.dist-info/RECORD
