Metadata-Version: 2.1
Name: odoo12-addon-beesdoo-website-theme
Version: 12.0.0.0.1.99.dev1
Summary: Apply BEES coop design rules.
Home-page: https://github.com/beescoop/Obeesdoo
Author: Rémy Taymans, Coop IT Easy SCRLfs
License: AGPL-3
Platform: UNKNOWN
Classifier: Programming Language :: Python
Classifier: Framework :: Odoo
Classifier: License :: OSI Approved :: GNU Affero General Public License v3
Requires-Python: >=3.5
Requires-Dist: odoo (<12.1dev,>=12.0a)
